galaxy/www/django/company/__init__.py
galaxy/www/django/company/apps.py
galaxy/www/django/company/models.py
galaxy/www/django/finance/__init__.py
galaxy/www/django/finance/apps.py
galaxy/www/django/finance/models.py
galaxy/www/django/infra/__init__.py
galaxy/www/django/infra/apps.py
galaxy/www/django/infra/models.py
galaxy/www/django/institution/__init__.py
galaxy/www/django/institution/apps.py
galaxy/www/django/institution/models.py
galaxy/www/django/iso/__init__.py
galaxy/www/django/iso/admin.py
galaxy/www/django/iso/apps.py
galaxy/www/django/iso/models.py
galaxy/www/django/prog/__init__.py
galaxy/www/django/prog/apps.py
galaxy/www/django/prog/models.py
galaxy/www/django/time/__init__.py
galaxy/www/django/time/apps.py
galaxy/www/django/time/models.py
galaxy/www/django/trading/__init__.py
galaxy/www/django/trading/apps.py
galaxy/www/django/trading/models.py
galaxy/www/flask/.gitignore
galaxy_py_www-0.0.6.dist-info/AUTHORS
galaxy_py_www-0.0.6.dist-info/COPYING.md
galaxy_py_www-0.0.6.dist-info/LICENSE.txt
galaxy_py_www-0.0.6.dist-info/METADATA
galaxy_py_www-0.0.6.dist-info/WHEEL
galaxy_py_www-0.0.6.dist-info/RECORD
