Metadata-Version: 2.3
Name: galaxy-py-www
Version: 0.0.6
Summary: Python Web for the Galaxy Project
License: Apache-2.0
Keywords: galaxy,galaxy-www
Author: Bastien Saltel
Author-email: bastien.saltel@gmail.com
Maintainer: Bastien Saltel
Maintainer-email: bastien.saltel@gmail.com
Requires-Python: >=3.10,<4.0
Classifier: Development Status :: 3 - Alpha
Classifier: Programming Language :: Python :: 3
Classifier: Operating System :: OS Independent
Requires-Dist: django
Requires-Dist: galaxy-py-data
Project-URL: Changelog, https://github.com/bsaltel/galaxy-py-www/blob/main/CHANGELOG.md
Project-URL: Documentation, https://github.com/bsaltel/galaxy-py-www
Project-URL: Homepage, https://github.com/bsaltel/galaxy-py-www
Project-URL: Issues, https://github.com/bsaltel/galaxy-py-www/issues
Project-URL: Repository, https://github.com/bsaltel/galaxy-py-www.git
